{
  "sources": [
    {
      "name": "Shipt Birmingham",
      "type": "workday",
      "pageUrl": "https://shipt.wd1.myworkdayjobs.com/Shipt_External",
      "apiBaseUrl": "https://shipt.wd1.myworkdayjobs.com/wday/cxs/shipt/Shipt_External",
      "companyName": "Shipt",
      "companyWebsite": "https://www.shipt.com",
      "sourceWeight": 14,
      "maxAccepted": 6,
      "requestLimit": 20,
      "requestOffsets": [
        0
      ],
      "requestDelayMs": 200,
      "allowedLocationPatterns": [
        "Birmingham, AL",
        "US Remote",
        "Remote"
      ],
      "locationRules": [
        {
          "match": "Birmingham, AL",
          "locationState": "Alabama",
          "locationRegion": "Central Alabama",
          "locationCity": "Birmingham"
        },
        {
          "match": "US Remote",
          "locationState": "Alabama",
          "locationRegion": "Central Alabama",
          "locationCity": "Remote",
          "remoteFriendly": true,
          "locationNotes": "Remote role from Birmingham startup"
        },
        {
          "match": "Remote",
          "locationState": "Alabama",
          "locationRegion": "Central Alabama",
          "locationCity": "Remote",
          "remoteFriendly": true,
          "locationNotes": "Remote role from Birmingham startup"
        }
      ],
      "includeKeywords": [
        "engineer",
        "security",
        "data",
        "application",
        "product manager",
        "project manager",
        "technical program manager",
        "scrum",
        "software",
        "analytics",
        "business intelligence",
        "technical writer",
        "documentation",
        "knowledge base",
        "help center",
        "technical account",
        "customer success",
        "implementation",
        "systems administrator",
        "support engineer",
        "seo",
        "growth",
        "marketing operations"
      ],
      "titleOrDepartmentIncludeKeywords": [
        "engineer",
        "security",
        "data",
        "analytics",
        "business intelligence",
        "product manager",
        "application",
        "project manager",
        "technical program manager",
        "technical writer",
        "documentation",
        "technical account",
        "customer success",
        "implementation",
        "systems administrator",
        "support engineer",
        "seo",
        "growth",
        "marketing operations"
      ],
      "titleOrDepartmentExcludeKeywords": [
        "finance",
        "counsel",
        "workforce",
        "retail media",
        "account executive",
        "field marketing",
        "broker",
        "claims"
      ]
    }
  ]
}
